playground/__init__.py
playground/bigquery.py
h4_test-0.0.11.dist-info/METADATA
h4_test-0.0.11.dist-info/WHEEL
h4_test-0.0.11.dist-info/top_level.txt
h4_test-0.0.11.dist-info/RECORD
