Metadata-Version: 2.4
Name: h4_test
Version: 0.0.11
Author-email: "h4.heo" <mungeol.heo@gmail.com>
Requires-Python: >=3.10
Requires-Dist: google-cloud-bigquery
